pytorch_stack-0.0.0.dev0.dist-info/licenses/LICENSE
torch_stack/__init__.py
torch_stack/__main__.py
torch_stack/debug.py
torch_stack/resolver.py
pytorch_stack-0.0.0.dev0.dist-info/METADATA
pytorch_stack-0.0.0.dev0.dist-info/WHEEL
pytorch_stack-0.0.0.dev0.dist-info/entry_points.txt
pytorch_stack-0.0.0.dev0.dist-info/top_level.txt
pytorch_stack-0.0.0.dev0.dist-info/RECORD
