Metadata-Version: 2.4
Name: pytorch-stack
Version: 0.0.0.dev0
Summary: A PyTorch stack utility package
Author-email: Jirka Borovec <jborovec+github@gmail.com>
License-Expression: Apache-2.0
Classifier: Programming Language :: Python :: 3 :: Only
Classifier: Programming Language :: Python :: 3.9
Classifier: Programming Language :: Python :: 3.10
Classifier: Programming Language :: Python :: 3.11
Classifier: Programming Language :: Python :: 3.12
Classifier: Programming Language :: Python :: 3.13
Requires-Python: >=3.9
License-File: LICENSE
Requires-Dist: torch==2.0.0
Provides-Extra: all
Requires-Dist: torchaudio; extra == "all"
Requires-Dist: torchtext; extra == "all"
Requires-Dist: torchvision; extra == "all"
Provides-Extra: audio
Requires-Dist: torchaudio; extra == "audio"
Provides-Extra: dev
Requires-Dist: jsonargparse[signatures]>=4.38; extra == "dev"
Requires-Dist: tomlkit; extra == "dev"
Provides-Extra: text
Requires-Dist: torchtext; extra == "text"
Provides-Extra: vision
Requires-Dist: torchvision; extra == "vision"
Dynamic: license-file
